{
  "_comment": "Alias → expansion map for search. Keys are matched against the whole normalized query or individual tokens.",
  "aliases": {
    "mcu": "marvel",
    "dcu": "dc",
    "dceu": "dc",
    "lotr": "lord of the rings",
    "hp": "harry potter",
    "got": "game of thrones",
    "hotd": "house of the dragon",
    "tlou": "the last of us",
    "aot": "attack on titan",
    "fmab": "fullmetal alchemist brotherhood",
    "jjk": "jujutsu kaisen",
    "mha": "my hero academia",
    "opm": "one punch man",
    "dbz": "dragon ball z",
    "hxh": "hunter x hunter",
    "snk": "attack on titan",
    "bb": "breaking bad",
    "bcs": "better call saul",
    "himym": "how i met your mother",
    "tbbt": "the big bang theory",
    "b99": "brooklyn nine nine",
    "twd": "the walking dead",
    "sw": "star wars",
    "st": "stranger things",
    "potc": "pirates of the caribbean",
    "fnaf": "five nights at freddys",
    "lok": "legend of korra",
    "atla": "avatar the last airbender",
    "jw": "jurassic world",
    "mib": "men in black",
    "ff": "fast and furious",
    "xmen": "x-men",
    "gotg": "guardians of the galaxy",
    "endgame": "avengers endgame",
    "infinity war": "avengers infinity war",
    "demon slayer": "demon slayer kimetsu no yaiba"
  }
}
